TLCount
