Metadata-Version: 1.0
Name: textLine-count
Version: 0.3
Summary: a small program that could count code line numbers
Home-page: https://github.com/amazing-tiantian
Author: tiantian
Author-email: tianzhuo_sd@163.com
License: MIT
Keywords: python line count
Platform: UNKNOWN
